{
    "_comment": "Created by PaulCK on 6/3/2018.",
    "type": "FeatureCollection",
    "features": [
        {
            "type": "Feature",
            "geometry": {
                "type": "Polygon",
                "coordinates": [
                    [
                        [
                            114.198249816895,
                            22.2587871551513
                        ],
                        [
                            114.198211669922,
                            22.2585849761963
                        ],
                        [
                            114.197288513184,
                            22.2582740783692
                        ],
                        [
                            114.196952819824,
                            22.2581634521485
                        ],
                        [
                            114.195686340332,
                            22.2577419281006
                        ],
                        [
                            114.192741394043,
                            22.2573223114014
                        ],
                        [
                            114.189796447754,
                            22.2564792633057
                        ],
                        [
                            114.186004638672,
                            22.2552165985107
                        ],
                        [
                            114.18431854248,
                            22.2556381225586
                        ],
                        [
                            114.180953979492,
                            22.2560577392579
                        ],
                        [
                            114.179267883301,
                            22.2577419281006
                        ],
                        [
                            114.177581787109,
                            22.2577419281006
                        ],
                        [
                            114.17716217041,
                            22.2564792633057
                        ],
                        [
                            114.175903320312,
                            22.2560577392579
                        ],
                        [
                            114.174217224121,
                            22.2564792633057
                        ],
                        [
                            114.170425415039,
                            22.2573223114014
                        ],
                        [
                            114.169166564942,
                            22.2581634521485
                        ],
                        [
                            114.167060852051,
                            22.2590045928956
                        ],
                        [
                            114.165794372559,
                            22.2594261169434
                        ],
                        [
                            114.164535522461,
                            22.2598476409913
                        ],
                        [
                            114.164398193359,
                            22.2599868774413
                        ],
                        [
                            114.163688659668,
                            22.2606887817384
                        ],
                        [
                            114.164505004883,
                            22.2615013122559
                        ],
                        [
                            114.165374755859,
                            22.262794494629
                        ],
                        [
                            114.165794372559,
                            22.2640571594239
                        ],
                        [
                            114.166221618652,
                            22.2661628723146
                        ],
                        [
                            114.165794372559,
                            22.2674255371093
                        ],
                        [
                            114.165794372559,
                            22.2686882019043
                        ],
                        [
                            114.165794372559,
                            22.2699508666992
                        ],
                        [
                            114.166221618652,
                            22.2712135314942
                        ],
                        [
                            114.166641235352,
                            22.2733192443848
                        ],
                        [
                            114.16828918457,
                            22.2749729156494
                        ],
                        [
                            114.16828918457,
                            22.2762317657472
                        ],
                        [
                            114.168319702148,
                            22.2786540985107
                        ],
                        [
                            114.168182373047,
                            22.2788486480713
                        ],
                        [
                            114.16724395752,
                            22.2803840637208
                        ],
                        [
                            114.167129516602,
                            22.2808628082275
                        ],
                        [
                            114.166976928711,
                            22.2815284729004
                        ],
                        [
                            114.168075561523,
                            22.2815284729004
                        ],
                        [
                            114.168472290039,
                            22.2815284729004
                        ],
                        [
                            114.168472290039,
                            22.2818050384522
                        ],
                        [
                            114.171249389649,
                            22.2818050384522
                        ],
                        [
                            114.171249389649,
                            22.2829170227052
                        ],
                        [
                            114.171524047852,
                            22.2829170227052
                        ],
                        [
                            114.171524047852,
                            22.2848606109619
                        ],
                        [
                            114.172080993652,
                            22.2848606109619
                        ],
                        [
                            114.172080993652,
                            22.2845821380615
                        ],
                        [
                            114.173194885254,
                            22.2845821380615
                        ],
                        [
                            114.173194885254,
                            22.2848606109619
                        ],
                        [
                            114.173751831055,
                            22.2848606109619
                        ],
                        [
                            114.173751831055,
                            22.2845821380615
                        ],
                        [
                            114.174308776856,
                            22.2845821380615
                        ],
                        [
                            114.174308776856,
                            22.2848606109619
                        ],
                        [
                            114.174583435059,
                            22.2848606109619
                        ],
                        [
                            114.174583435059,
                            22.2843055725097
                        ],
                        [
                            114.174858093262,
                            22.2843055725097
                        ],
                        [
                            114.174858093262,
                            22.2840270996094
                        ],
                        [
                            114.174583435059,
                            22.2840270996094
                        ],
                        [
                            114.174583435059,
                            22.2837505340577
                        ],
                        [
                            114.174858093262,
                            22.2837505340577
                        ],
                        [
                            114.174858093262,
                            22.2829170227052
                        ],
                        [
                            114.175415039063,
                            22.2829170227052
                        ],
                        [
                            114.175415039063,
                            22.2826385498048
                        ],
                        [
                            114.176803588867,
                            22.2826385498048
                        ],
                        [
                            114.176803588867,
                            22.2829170227052
                        ],
                        [
                            114.177360534668,
                            22.2829170227052
                        ],
                        [
                            114.177360534668,
                            22.2831935882569
                        ],
                        [
                            114.177474975586,
                            22.2831935882569
                        ],
                        [
                            114.177635192871,
                            22.2831935882569
                        ],
                        [
                            114.177635192871,
                            22.2834720611573
                        ],
                        [
                            114.177917480469,
                            22.2834701538086
                        ],
                        [
                            114.180305480957,
                            22.2830715179443
                        ],
                        [
                            114.180473327637,
                            22.283042907715
                        ],
                        [
                            114.18212890625,
                            22.2832794189453
                        ],
                        [
                            114.182449340821,
                            22.2832317352295
                        ],
                        [
                            114.183044433594,
                            22.2833805084229
                        ],
                        [
                            114.183494567871,
                            22.2830791473389
                        ],
                        [
                            114.183601379395,
                            22.2830638885498
                        ],
                        [
                            114.184135437012,
                            22.2829837799072
                        ],
                        [
                            114.18537902832,
                            22.2828083038331
                        ],
                        [
                            114.187210083008,
                            22.2817420959473
                        ],
                        [
                            114.187446594238,
                            22.2808570861818
                        ],
                        [
                            114.187446594238,
                            22.2807159423829
                        ],
                        [
                            114.187553405762,
                            22.2807388305665
                        ],
                        [
                            114.188919067383,
                            22.2812843322754
                        ],
                        [
                            114.18970489502,
                            22.2815971374513
                        ],
                        [
                            114.19034576416,
                            22.2818546295167
                        ],
                        [
                            114.191024780273,
                            22.2821254730225
                        ],
                        [
                            114.191680908203,
                            22.2825603485108
                        ],
                        [
                            114.192008972168,
                            22.2827816009523
                        ],
                        [
                            114.192291259766,
                            22.2829685211182
                        ],
                        [
                            114.192489624023,
                            22.2821559906006
                        ],
                        [
                            114.192710876465,
                            22.2812843322754
                        ],
                        [
                            114.193969726563,
                            22.2804431915283
                        ],
                        [
                            114.194213867188,
                            22.279468536377
                        ],
                        [
                            114.194396972656,
                            22.2787609100343
                        ],
                        [
                            114.194679260254,
                            22.2780342102051
                        ],
                        [
                            114.195053100586,
                            22.2771110534668
                        ],
                        [
                            114.195343017578,
                            22.2765235900879
                        ],
                        [
                            114.197303771973,
                            22.2742385864259
                        ],
                        [
                            114.197372436524,
                            22.2741622924805
                        ],
                        [
                            114.197883605957,
                            22.2737846374513
                        ],
                        [
                            114.199447631836,
                            22.2745475769044
                        ],
                        [
                            114.200706481934,
                            22.2754058837892
                        ],
                        [
                            114.200706481934,
                            22.2756462097169
                        ],
                        [
                            114.200706481934,
                            22.276653289795
                        ],
                        [
                            114.201553344727,
                            22.277494430542
                        ],
                        [
                            114.202491760254,
                            22.2768669128417
                        ],
                        [
                            114.202812194824,
                            22.276653289795
                        ],
                        [
                            114.202911376953,
                            22.2765579223634
                        ],
                        [
                            114.203872680664,
                            22.2755966186525
                        ],
                        [
                            114.204048156738,
                            22.2755393981934
                        ],
                        [
                            114.204765319824,
                            22.2747669219971
                        ],
                        [
                            114.204872131348,
                            22.2746524810792
                        ],
                        [
                            114.206413269043,
                            22.2733535766602
                        ],
                        [
                            114.206825256348,
                            22.2726459503174
                        ],
                        [
                            114.206886291504,
                            22.2713451385499
                        ],
                        [
                            114.206474304199,
                            22.2703418731689
                        ],
                        [
                            114.205581665039,
                            22.2694530487062
                        ],
                        [
                            114.203872680664,
                            22.2680969238282
                        ],
                        [
                            114.202217102051,
                            22.266736984253
                        ],
                        [
                            114.200386047364,
                            22.2655544281006
                        ],
                        [
                            114.199203491211,
                            22.2649631500245
                        ],
                        [
                            114.199104309082,
                            22.2643680572511
                        ],
                        [
                            114.198738098145,
                            22.2620773315429
                        ],
                        [
                            114.198608398438,
                            22.261058807373
                        ],
                        [
                            114.198249816895,
                            22.2587871551513
                        ]
                    ]
                ]
            },
            "properties": {
                "name": "Wan Chai",
                "styleUrl": "#15",
                "styleHash": "-2a68673b",
                "description": "District",
                "stroke": "#c8faff",
                "stroke-opacity": 1,
                "stroke-width": 0,
                "fill": "#c8faff",
                "fill-opacity": 0.5019607843137255,
                "visibility": "1"
            }
        }
    ]
}